hela/__init__.py
hela/_base_data_type.py
hela/_base_dataset.py
hela/_catalog_class.py
hela/_column_classes.py
hela/_column_store_class.py
hela/_constants.py
hela/_utils/__init__.py
hela/_utils/bigquery_utils.py
hela/_utils/date_utils.py
hela/_utils/dict_utils.py
hela/_utils/maps.py
hela/_utils/path_utils.py
hela/_utils/short_description.py
hela/data_types.py
hela/datasets/__init__.py
hela/datasets/bigquery_dataset.py
hela/datasets/pandas_parquet_dataset.py
hela/datasets/spark_parquet_dataset.py
hela/errors.py
hela/infer.py
hela/math/__init__.py
hela/math/levenshtein.py
hela/math/preprocessing.py
hela/math/score_info.py
hela/math/stopwords.txt
hela/math/tf_idf.py
hela/plots/__init__.py
hela/plots/date_plots.py
hela/plots/html_displays.py
hela/schema_generators.py
hela/test_suite/__init__.py
hela/test_suite/catalog_tests.py
hela/test_suite/column_store_tests.py
hela/test_suite/description_tests.py
hela/web_page/__init__.py
hela/web_page/_json_generator.py
hela/web_page/generate.py
hela/web_page/index.html.gz
hela-0.2.6.dist-info/LICENSE
hela-0.2.6.dist-info/METADATA
hela-0.2.6.dist-info/WHEEL
hela-0.2.6.dist-info/RECORD
