Metadata-Version: 2.1
Name: hela
Version: 0.2.6
Summary: Your data catalog as code and one schema to rule them all.
Home-page: https://github.com/erikmunkby/hela
License: Apache License v2.0
Keywords: data,catalog,big,web,deploy,aws,glue,bigquery,spark,democratize
Author: Erik Munkby
Author-email: erik.munkby@gmail.com
Requires-Python: >=3.9,<4.0
Classifier: License :: Other/Proprietary License
Classifier: Programming Language :: Python :: 3
Classifier: Programming Language :: Python :: 3.9
Classifier: Programming Language :: Python :: 3.10
Classifier: Programming Language :: Python :: 3.11
Provides-Extra: bigquery
Provides-Extra: glue
Provides-Extra: spark
Requires-Dist: Jinja2 (>=3.0.3,<4.0.0)
Requires-Dist: aws-cdk.aws-glue ; extra == "glue"
Requires-Dist: google-cloud-bigquery ; extra == "bigquery"
Requires-Dist: numpy (>=1,<2)
Requires-Dist: pandas (>=1,<3)
Requires-Dist: pyspark (>=3,<4) ; extra == "spark"
Project-URL: Repository, https://github.com/erikmunkby/hela
